wj_social_net_queries/__init__.py
wj_social_net_queries/connectors/api_connector.py
wj_social_net_queries/connectors/api_graph_connector.py
wj_social_net_queries/connectors/api_twitter_connector.py
wj_social_net_queries/connectors/rapid_api_connector.py
wj_social_net_queries/controllers/__init__.py
wj_social_net_queries/controllers/meta_controller.py
wj_social_net_queries/controllers/rapid_api_controller.py
wj_social_net_queries/controllers/twitter_controller.py
wj_social_net_queries/core/facebook.py
wj_social_net_queries/core/instagram.py
wj_social_net_queries/core/twitter.py
wj_social_net_queries/utils/AWS/s3.py
wj_social_net_queries/utils/constants/api_graph_constants.py
wj_social_net_queries/utils/constants/constants.py
wj_social_net_queries/utils/constants/rapid_api_constans.py
wj_social_net_queries/utils/ig_utils.py
wj_social_net_queries/utils/utils.py
wj_social_net_queries-0.15.0.dist-info/WHEEL
wj_social_net_queries-0.15.0.dist-info/METADATA
wj_social_net_queries-0.15.0.dist-info/RECORD
