Metadata-Version: 2.1
Name: wj-social-net-queries
Version: 0.15.0
Summary: this library is responsible for comunicating with social network API's for data interaction with Whale and Jaguar products
License: private
Author: w&j
Requires-Python: >=3.8,<3.10
Classifier: License :: Other/Proprietary License
Classifier: Programming Language :: Python :: 3
Classifier: Programming Language :: Python :: 3.8
Classifier: Programming Language :: Python :: 3.9
Requires-Dist: boto3 (>=1.24.45,<2.0.0)
Requires-Dist: certifi (==2022.6.15)
Requires-Dist: charset-normalizer (==2.1.0)
Requires-Dist: chromedriver-autoinstaller (>=0.4.0,<0.5.0)
Requires-Dist: idna (==3.3)
Requires-Dist: numpy (==1.21.3)
Requires-Dist: pandas (==1.3.2)
Requires-Dist: python-dateutil (==2.8.2)
Requires-Dist: python-dotenv (==0.20.0)
Requires-Dist: pytz (==2022.1)
Requires-Dist: requests (==2.28.1)
Requires-Dist: requests-oauthlib (>=1.3.1,<2.0.0)
Requires-Dist: selenium (>=4.4.3,<5.0.0)
Requires-Dist: six (==1.16.0)
Requires-Dist: tweepy (>=4.10.0,<5.0.0)
Requires-Dist: urllib3 (==1.26.11)
